python_simple_menu/__init__.py
python_simple_menu/examples/01_basic_usage.py
python_simple_menu/examples/02_custom_prompts.py
python_simple_menu/examples/__init__.py
python_simple_menu/items.py
python_simple_menu/menu.py
python_simple_menu-1.1.15.dist-info/LICENSE
python_simple_menu-1.1.15.dist-info/METADATA
python_simple_menu-1.1.15.dist-info/WHEEL
python_simple_menu-1.1.15.dist-info/RECORD
