Metadata-Version: 2.1
Name: python-simple-menu
Version: 1.1.15
Summary: Yet another simple console menu
License: MIT
Author: Chris Vann
Author-email: chrisvann01@gmail.com
Requires-Python: >=3.8,<4.0
Classifier: License :: OSI Approved :: MIT License
Classifier: Programming Language :: Python :: 3
Classifier: Programming Language :: Python :: 3.8
Classifier: Programming Language :: Python :: 3.9
Classifier: Programming Language :: Python :: 3.10
Classifier: Programming Language :: Python :: 3.11
